duck_test_pkg/__init__.py
duck_test_pkg-1.99.12.dist-info/METADATA
duck_test_pkg-1.99.12.dist-info/WHEEL
duck_test_pkg-1.99.12.dist-info/RECORD
