Metadata-Version: 2.1
Name: duck-test-pkg
Version: 1.99.12
Summary: Test Package used in SW Eng. training. Do not install.
Requires-Python: >=3.11,<4.0
Classifier: Programming Language :: Python :: 3
Classifier: Programming Language :: Python :: 3.11
